{
  "generated": "2026-07-16T22:16:12.669022+00:00",
  "as_of": "2026-07-16",
  "source": "tradier",
  "overall": {
    "trades": 0,
    "wins": 0,
    "losses": 0,
    "win_rate": null,
    "profit_factor": null,
    "avg_win": null,
    "avg_loss": null,
    "expectancy": null,
    "total_pl": 0
  },
  "long_calls": {
    "trades": 0,
    "wins": 0,
    "losses": 0,
    "win_rate": null,
    "profit_factor": null,
    "avg_win": null,
    "avg_loss": null,
    "expectancy": null,
    "total_pl": 0,
    "open_positions": 77,
    "open_pl": -20925.5,
    "insights": [
      "No closed trades yet in Long Call \u2014 metrics will populate as positions resolve.",
      "22 open position(s) inside 21 DTE \u2014 decay is now the dominant force on these; each day held is a real cost."
    ]
  },
  "strategies": {},
  "groups": {
    "1 Samurai Scan First": {
      "label": "1 Samurai Scan First",
      "trades": 0,
      "wins": 0,
      "losses": 0,
      "win_rate": null,
      "profit_factor": null,
      "avg_win": null,
      "avg_loss": null,
      "expectancy": null,
      "total_pl": 0,
      "open_positions": 25,
      "open_pl": 2937.5,
      "insights": [
        "No closed trades yet in 1 Samurai Scan First \u2014 metrics will populate as positions resolve.",
        "22 open position(s) inside 21 DTE \u2014 decay is now the dominant force on these; each day held is a real cost."
      ]
    },
    "GG_Core Leadership": {
      "label": "GG_Core Leadership",
      "trades": 0,
      "wins": 0,
      "losses": 0,
      "win_rate": null,
      "profit_factor": null,
      "avg_win": null,
      "avg_loss": null,
      "expectancy": null,
      "total_pl": 0,
      "open_positions": 1,
      "open_pl": -860.0,
      "insights": [
        "No closed trades yet in GG_Core Leadership \u2014 metrics will populate as positions resolve.",
        "All 1 open position(s) are underwater \u2014 no confirmation yet that this batch of entries is working."
      ]
    },
    "GG_High Relative Strength": {
      "label": "GG_High Relative Strength",
      "trades": 0,
      "wins": 0,
      "losses": 0,
      "win_rate": null,
      "profit_factor": null,
      "avg_win": null,
      "avg_loss": null,
      "expectancy": null,
      "total_pl": 0,
      "open_positions": 39,
      "open_pl": 2102.5,
      "insights": [
        "No closed trades yet in GG_High Relative Strength \u2014 metrics will populate as positions resolve."
      ]
    },
    "GG_Positive Expectancy": {
      "label": "GG_Positive Expectancy",
      "trades": 0,
      "wins": 0,
      "losses": 0,
      "win_rate": null,
      "profit_factor": null,
      "avg_win": null,
      "avg_loss": null,
      "expectancy": null,
      "total_pl": 0,
      "open_positions": 12,
      "open_pl": -25105.5,
      "insights": [
        "No closed trades yet in GG_Positive Expectancy \u2014 metrics will populate as positions resolve.",
        "Only 17% of open positions are currently profitable \u2014 this batch is fighting the tape more than the historical win rate suggests."
      ]
    }
  },
  "open": [
    {
      "id": "SAM1-NVDA-192_5C-0717",
      "symbol": "NVDA",
      "strategy": "long_call",
      "strategy_label": "Long Call",
      "group": "1 Samurai Scan First",
      "buy_date": "2026-07-01",
      "expiration": "2026-07-17",
      "dte": 1,
      "contracts": 1,
      "legs": [
        {
          "type": "call",
          "side": "long",
          "strike": 192.5,
          "qty": 1
        }
      ],
      "entry_price": 9.33,
      "mark": 15.075,
      "pl": 574.5,
      "pl_pct": 61.6,
      "technicals": {
        "price": 207.4,
        "rsi": 52.1,
        "sma20": 202.22,
        "sma50": 209.79,
        "macd_hist": 1.7
      },
      "sparkline": [
        7.225,
        7.225,
        7.15,
        7.95,
        13.475,
        11.65,
        18.875,
        11.825,
        19.6,
        20.025,
        15.075
      ],
      "recommendations": [
        {
          "level": "watch",
          "text": "Up 62% \u2014 profit-target zone. A trailing exit (e.g., give back no more than a third) protects gains."
        },
        {
          "level": "warn",
          "text": "1 DTE \u2014 final-week gamma/theta zone. Close or roll unless you want an expiration outcome."
        },
        {
          "level": "warn",
          "text": "Underlying is below its 50-day SMA \u2014 intermediate trend is down; bullish premium is fighting the tape."
        }
      ],
      "notes": ""
    },
    {
      "id": "SAM1-CRM-160C-0717",
      "symbol": "CRM",
      "strategy": "long_call",
      "strategy_label": "Long Call",
      "group": "1 Samurai Scan First",
      "buy_date": "2026-07-01",
      "expiration": "2026-07-17",
      "dte": 1,
      "contracts": 1,
      "legs": [
        {
          "type": "call",
          "side": "long",
          "strike": 160.0,
          "qty": 1
        }
      ],
      "entry_price": 7.58,
      "mark": 12.625,
      "pl": 504.5,
      "pl_pct": 66.6,
      "technicals": {
        "price": 172.68,
        "rsi": 56.1,
        "sma20": 161.08,
        "sma50": 171.91,
        "macd_hist": 1.881
      },
      "sparkline": [
        9.175,
        9.175,
        8.725,
        11.275,
        8.65,
        5.4,
        5.5,
        11.375,
        8.075,
        7.7,
        12.625
      ],
      "recommendations": [
        {
          "level": "watch",
          "text": "Up 67% \u2014 profit-target zone. A trailing exit (e.g., give back no more than a third) protects gains."
        },
        {
          "level": "warn",
          "text": "1 DTE \u2014 final-week gamma/theta zone. Close or roll unless you want an expiration outcome."
        }
      ],
      "notes": ""
    },
    {
      "id": "SAM1-PLTR-122C-0717",
      "symbol": "PLTR",
      "strategy": "long_call",
      "strategy_label": "Long Call",
      "group": "1 Samurai Scan First",
      "buy_date": "2026-07-01",
      "expiration": "2026-07-17",
      "dte": 1,
      "contracts": 1,
      "legs": [
        {
          "type": "call",
          "side": "long",
          "strike": 122.0,
          "qty": 1
        }
      ],
      "entry_price": 7.55,
      "mark": 12.35,
      "pl": 480.0,
      "pl_pct": 63.6,
      "technicals": {
        "price": 134.44,
        "rsi": 55.7,
        "sma20": 125.17,
        "sma50": 132.55,
        "macd_hist": 1.749
      },
      "sparkline": [
        9.95,
        9.95,
        11.95,
        13.625,
        11.325,
        8.45,
        6.275,
        8.825,
        12.2,
        12.0,
        12.35
      ],
      "recommendations": [
        {
          "level": "watch",
          "text": "Up 64% \u2014 profit-target zone. A trailing exit (e.g., give back no more than a third) protects gains."
        },
        {
          "level": "warn",
          "text": "1 DTE \u2014 final-week gamma/theta zone. Close or roll unless you want an expiration outcome."
        }
      ],
      "notes": ""
    },
    {
      "id": "SAM1-TSLA-415C-0717",
      "symbol": "TSLA",
      "strategy": "long_call",
      "strategy_label": "Long Call",
      "group": "1 Samurai Scan First",
      "buy_date": "2026-07-01",
      "expiration": "2026-07-17",
      "dte": 1,
      "contracts": 1,
      "legs": [
        {
          "type": "call",
          "side": "long",
          "strike": 415.0,
          "qty": 1
        }
      ],
      "entry_price": 21.53,
      "mark": 0.145,
      "pl": -2138.5,
      "pl_pct": -99.3,
      "technicals": {
        "price": 391.06,
        "rsi": 46.0,
        "sma20": 398.63,
        "sma50": 409.97,
        "macd_hist": -0.818
      },
      "sparkline": [
        6.1,
        6.1,
        16.15,
        7.9,
        4.25,
        7.15,
        6.45,
        1.845,
        1.325,
        0.645,
        0.145
      ],
      "recommendations": [
        {
          "level": "action",
          "text": "Down 99% \u2014 standard long-premium stop is \u221250%; theta will keep working against the position."
        },
        {
          "level": "warn",
          "text": "1 DTE and underwater \u2014 time decay steepens from here; the probability of recovery drops sharply."
        },
        {
          "level": "warn",
          "text": "Underlying closed below its 20-day SMA \u2014 short-term trend no longer supports the bullish thesis."
        },
        {
          "level": "warn",
          "text": "Underlying is below its 50-day SMA \u2014 intermediate trend is down; bullish premium is fighting the tape."
        },
        {
          "level": "watch",
          "text": "MACD histogram negative \u2014 bullish momentum fading on the daily chart."
        }
      ],
      "notes": ""
    },
    {
      "id": "SAM1-KHC-25C-0717",
      "symbol": "KHC",
      "strategy": "long_call",
      "strategy_label": "Long Call",
      "group": "1 Samurai Scan First",
      "buy_date": "2026-07-01",
      "expiration": "2026-07-17",
      "dte": 1,
      "contracts": 1,
      "legs": [
        {
          "type": "call",
          "side": "long",
          "strike": 25.0,
          "qty": 1
        }
      ],
      "entry_price": 0.55,
      "mark": 1.22,
      "pl": 67.0,
      "pl_pct": 121.8,
      "technicals": {
        "price": 26.23,
        "rsi": 66.4,
        "sma20": 24.27,
        "sma50": 23.82,
        "macd_hist": 0.142
      },
      "sparkline": [
        0.765,
        0.765,
        0.425,
        0.75,
        0.44,
        0.285,
        0.305,
        0.465,
        0.405,
        0.595,
        1.22
      ],
      "recommendations": [
        {
          "level": "action",
          "text": "Up 122% \u2014 consider taking profit or selling half to lock in the original debit."
        },
        {
          "level": "warn",
          "text": "1 DTE \u2014 final-week gamma/theta zone. Close or roll unless you want an expiration outcome."
        }
      ],
      "notes": ""
    },
    {
      "id": "SAM1-AVGO-370C-0717",
      "symbol": "AVGO",
      "strategy": "long_call",
      "strategy_label": "Long Call",
      "group": "1 Samurai Scan First",
      "buy_date": "2026-07-01",
      "expiration": "2026-07-17",
      "dte": 1,
      "contracts": 1,
      "legs": [
        {
          "type": "call",
          "side": "long",
          "strike": 370.0,
          "qty": 1
        }
      ],
      "entry_price": 14.4,
      "mark": 7.575,
      "pl": -682.5,
      "pl_pct": -47.4,
      "technicals": {
        "price": 374.45,
        "rsi": 45.0,
        "sma20": 382.94,
        "sma50": 404.07,
        "macd_hist": 1.926
      },
      "sparkline": [
        9.925,
        9.925,
        15.65,
        12.95,
        24.9,
        34.15,
        31.7,
        17.75,
        21.3,
        25.1,
        7.575
      ],
      "recommendations": [
        {
          "level": "warn",
          "text": "1 DTE and underwater \u2014 time decay steepens from here; the probability of recovery drops sharply."
        },
        {
          "level": "warn",
          "text": "Underlying closed below its 20-day SMA \u2014 short-term trend no longer supports the bullish thesis."
        },
        {
          "level": "warn",
          "text": "Underlying is below its 50-day SMA \u2014 intermediate trend is down; bullish premium is fighting the tape."
        }
      ],
      "notes": ""
    },
    {
      "id": "SAM1-UBER-72_5C-0717",
      "symbol": "UBER",
      "strategy": "long_call",
      "strategy_label": "Long Call",
      "group": "1 Samurai Scan First",
      "buy_date": "2026-07-01",
      "expiration": "2026-07-17",
      "dte": 1,
      "contracts": 1,
      "legs": [
        {
          "type": "call",
          "side": "long",
          "strike": 72.5,
          "qty": 1
        }
      ],
      "entry_price": 2.25,
      "mark": 1.725,
      "pl": -52.5,
      "pl_pct": -23.3,
      "technicals": {
        "price": 74.04,
        "rsi": 52.7,
        "sma20": 73.15,
        "sma50": 72.98,
        "macd_hist": -0.003
      },
      "sparkline": [
        3.275,
        3.275,
        1.935,
        2.905,
        2.355,
        2.72,
        2.67,
        2.39,
        0.9,
        1.05,
        1.725
      ],
      "recommendations": [
        {
          "level": "warn",
          "text": "1 DTE and underwater \u2014 time decay steepens from here; the probability of recovery drops sharply."
        },
        {
          "level": "watch",
          "text": "MACD histogram negative \u2014 bullish momentum fading on the daily chart."
        }
      ],
      "notes": ""
    },
    {
      "id": "SAM1-BABA-97C-0717",
      "symbol": "BABA",
      "strategy": "long_call",
      "strategy_label": "Long Call",
      "group": "1 Samurai Scan First",
      "buy_date": "2026-07-01",
      "expiration": "2026-07-17",
      "dte": 1,
      "contracts": 1,
      "legs": [
        {
          "type": "call",
          "side": "long",
          "strike": 97.0,
          "qty": 1
        }
      ],
      "entry_price": 4.23,
      "mark": 21.45,
      "pl": 1722.0,
      "pl_pct": 407.1,
      "technicals": {
        "price": 117.49,
        "rsi": 62.5,
        "sma20": 104.29,
        "sma50": 118.76,
        "macd_hist": 3.077
      },
      "sparkline": [
        3.1,
        3.1,
        3.775,
        3.7,
        12.35,
        14.375,
        14.9,
        15.4,
        15.225,
        20.75,
        21.45
      ],
      "recommendations": [
        {
          "level": "action",
          "text": "Up 407% \u2014 consider taking profit or selling half to lock in the original debit."
        },
        {
          "level": "warn",
          "text": "1 DTE \u2014 final-week gamma/theta zone. Close or roll unless you want an expiration outcome."
        },
        {
          "level": "warn",
          "text": "Underlying is below its 50-day SMA \u2014 intermediate trend is down; bullish premium is fighting the tape."
        }
      ],
      "notes": ""
    },
    {
      "id": "SAM1-BAC-57_5C-0717",
      "symbol": "BAC",
      "strategy": "long_call",
      "strategy_label": "Long Call",
      "group": "1 Samurai Scan First",
      "buy_date": "2026-07-01",
      "expiration": "2026-07-17",
      "dte": 1,
      "contracts": 1,
      "legs": [
        {
          "type": "call",
          "side": "long",
          "strike": 57.5,
          "qty": 1
        }
      ],
      "entry_price": 1.95,
      "mark": 3.975,
      "pl": 202.5,
      "pl_pct": 103.8,
      "technicals": {
        "price": 61.49,
        "rsi": 72.1,
        "sma20": 58.7,
        "sma50": 54.95,
        "macd_hist": 0.119
      },
      "sparkline": [
        2.115,
        2.115,
        2.895,
        2.86,
        1.705,
        2.275,
        2.51,
        2.365,
        3.2,
        4.125,
        3.975
      ],
      "recommendations": [
        {
          "level": "action",
          "text": "Up 104% \u2014 consider taking profit or selling half to lock in the original debit."
        },
        {
          "level": "warn",
          "text": "1 DTE \u2014 final-week gamma/theta zone. Close or roll unless you want an expiration outcome."
        },
        {
          "level": "watch",
          "text": "RSI 72 (overbought) \u2014 momentum stretched; a scale-out here often beats waiting for the pullback."
        }
      ],
      "notes": ""
    },
    {
      "id": "SAM1-AVGO-350C-0717-0702",
      "symbol": "AVGO",
      "strategy": "long_call",
      "strategy_label": "Long Call",
      "group": "1 Samurai Scan First",
      "buy_date": "2026-07-02",
      "expiration": "2026-07-17",
      "dte": 1,
      "contracts": 1,
      "legs": [
        {
          "type": "call",
          "side": "long",
          "strike": 350.0,
          "qty": 1
        }
      ],
      "entry_price": 20.33,
      "mark": 24.65,
      "pl": 432.0,
      "pl_pct": 21.2,
      "technicals": {
        "price": 374.45,
        "rsi": 45.0,
        "sma20": 382.94,
        "sma50": 404.07,
        "macd_hist": 1.926
      },
      "sparkline": [
        20.325,
        29.0,
        25.8,
        41.275,
        52.4,
        50.825,
        35.375,
        40.475,
        44.7,
        24.65
      ],
      "recommendations": [
        {
          "level": "warn",
          "text": "1 DTE \u2014 final-week gamma/theta zone. Close or roll unless you want an expiration outcome."
        },
        {
          "level": "warn",
          "text": "Underlying closed below its 20-day SMA \u2014 short-term trend no longer supports the bullish thesis."
        },
        {
          "level": "warn",
          "text": "Underlying is below its 50-day SMA \u2014 intermediate trend is down; bullish premium is fighting the tape."
        }
      ],
      "notes": ""
    },
    {
      "id": "SAM1-NVDA-190C-0717-0702",
      "symbol": "NVDA",
      "strategy": "long_call",
      "strategy_label": "Long Call",
      "group": "1 Samurai Scan First",
      "buy_date": "2026-07-02",
      "expiration": "2026-07-17",
      "dte": 1,
      "contracts": 1,
      "legs": [
        {
          "type": "call",
          "side": "long",
          "strike": 190.0,
          "qty": 1
        }
      ],
      "entry_price": 8.78,
      "mark": 17.2,
      "pl": 842.0,
      "pl_pct": 95.9,
      "technicals": {
        "price": 207.4,
        "rsi": 52.1,
        "sma20": 202.22,
        "sma50": 209.79,
        "macd_hist": 1.7
      },
      "sparkline": [
        8.775,
        8.75,
        9.725,
        15.525,
        13.825,
        21.4,
        14.1,
        22.05,
        22.575,
        17.2
      ],
      "recommendations": [
        {
          "level": "watch",
          "text": "Up 96% \u2014 profit-target zone. A trailing exit (e.g., give back no more than a third) protects gains."
        },
        {
          "level": "warn",
          "text": "1 DTE \u2014 final-week gamma/theta zone. Close or roll unless you want an expiration outcome."
        },
        {
          "level": "warn",
          "text": "Underlying is below its 50-day SMA \u2014 intermediate trend is down; bullish premium is fighting the tape."
        }
      ],
      "notes": ""
    },
    {
      "id": "SAM1-TSLA-385C-0717-0702",
      "symbol": "TSLA",
      "strategy": "long_call",
      "strategy_label": "Long Call",
      "group": "1 Samurai Scan First",
      "buy_date": "2026-07-02",
      "expiration": "2026-07-17",
      "dte": 1,
      "contracts": 1,
      "legs": [
        {
          "type": "call",
          "side": "long",
          "strike": 385.0,
          "qty": 1
        }
      ],
      "entry_price": 18.58,
      "mark": 7.775,
      "pl": -1080.5,
      "pl_pct": -58.2,
      "technicals": {
        "price": 391.06,
        "rsi": 46.0,
        "sma20": 398.63,
        "sma50": 409.97,
        "macd_hist": -0.818
      },
      "sparkline": [
        18.575,
        38.075,
        23.875,
        16.55,
        25.025,
        25.3,
        13.95,
        13.825,
        11.55,
        7.775
      ],
      "recommendations": [
        {
          "level": "action",
          "text": "Down 58% \u2014 standard long-premium stop is \u221250%; theta will keep working against the position."
        },
        {
          "level": "warn",
          "text": "1 DTE and underwater \u2014 time decay steepens from here; the probability of recovery drops sharply."
        },
        {
          "level": "warn",
          "text": "Underlying closed below its 20-day SMA \u2014 short-term trend no longer supports the bullish thesis."
        },
        {
          "level": "warn",
          "text": "Underlying is below its 50-day SMA \u2014 intermediate trend is down; bullish premium is fighting the tape."
        },
        {
          "level": "watch",
          "text": "MACD histogram negative \u2014 bullish momentum fading on the daily chart."
        }
      ],
      "notes": ""
    },
    {
      "id": "SAM1-CRM-165C-0717-0702",
      "symbol": "CRM",
      "strategy": "long_call",
      "strategy_label": "Long Call",
      "group": "1 Samurai Scan First",
      "buy_date": "2026-07-02",
      "expiration": "2026-07-17",
      "dte": 1,
      "contracts": 1,
      "legs": [
        {
          "type": "call",
          "side": "long",
          "strike": 165.0,
          "qty": 1
        }
      ],
      "entry_price": 6.18,
      "mark": 7.85,
      "pl": 167.0,
      "pl_pct": 27.0,
      "technicals": {
        "price": 172.68,
        "rsi": 56.1,
        "sma20": 161.08,
        "sma50": 171.91,
        "macd_hist": 1.881
      },
      "sparkline": [
        6.175,
        5.725,
        7.725,
        5.45,
        2.885,
        2.765,
        7.9,
        4.6,
        3.6,
        7.85
      ],
      "recommendations": [
        {
          "level": "warn",
          "text": "1 DTE \u2014 final-week gamma/theta zone. Close or roll unless you want an expiration outcome."
        }
      ],
      "notes": ""
    },
    {
      "id": "SAM1-LYFT-15C-0717-0702",
      "symbol": "LYFT",
      "strategy": "long_call",
      "strategy_label": "Long Call",
      "group": "1 Samurai Scan First",
      "buy_date": "2026-07-02",
      "expiration": "2026-07-17",
      "dte": 1,
      "contracts": 1,
      "legs": [
        {
          "type": "call",
          "side": "long",
          "strike": 15.0,
          "qty": 1
        }
      ],
      "entry_price": 0.8,
      "mark": 1.075,
      "pl": 27.5,
      "pl_pct": 34.4,
      "technicals": {
        "price": 15.98,
        "rsi": 63.0,
        "sma20": 15.01,
        "sma50": 14.3,
        "macd_hist": 0.092
      },
      "sparkline": [
        0.795,
        0.8,
        0.785,
        0.595,
        0.925,
        0.765,
        0.785,
        0.74,
        1.305,
        1.075
      ],
      "recommendations": [
        {
          "level": "warn",
          "text": "1 DTE \u2014 final-week gamma/theta zone. Close or roll unless you want an expiration outcome."
        }
      ],
      "notes": ""
    },
    {
      "id": "SAM1-PLTR-127C-0717-0702",
      "symbol": "PLTR",
      "strategy": "long_call",
      "strategy_label": "Long Call",
      "group": "1 Samurai Scan First",
      "buy_date": "2026-07-02",
      "expiration": "2026-07-17",
      "dte": 1,
      "contracts": 1,
      "legs": [
        {
          "type": "call",
          "side": "long",
          "strike": 127.0,
          "qty": 1
        }
      ],
      "entry_price": 6.7,
      "mark": 7.55,
      "pl": 85.0,
      "pl_pct": 12.7,
      "technicals": {
        "price": 134.44,
        "rsi": 55.7,
        "sma20": 125.17,
        "sma50": 132.55,
        "macd_hist": 1.749
      },
      "sparkline": [
        6.7,
        8.325,
        9.675,
        7.55,
        5.05,
        3.2,
        5.0,
        7.6,
        7.025,
        7.55
      ],
      "recommendations": [
        {
          "level": "warn",
          "text": "1 DTE \u2014 final-week gamma/theta zone. Close or roll unless you want an expiration outcome."
        }
      ],
      "notes": ""
    },
    {
      "id": "SAM1-WMT-111C-0717-0702",
      "symbol": "WMT",
      "strategy": "long_call",
      "strategy_label": "Long Call",
      "group": "1 Samurai Scan First",
      "buy_date": "2026-07-02",
      "expiration": "2026-07-17",
      "dte": 1,
      "contracts": 1,
      "legs": [
        {
          "type": "call",
          "side": "long",
          "strike": 111.0,
          "qty": 1
        }
      ],
      "entry_price": 2.72,
      "mark": 4.85,
      "pl": 213.0,
      "pl_pct": 78.3,
      "technicals": {
        "price": 114.95,
        "rsi": 48.1,
        "sma20": 114.41,
        "sma50": 119.97,
        "macd_hist": 0.452
      },
      "sparkline": [
        2.72,
        1.93,
        2.305,
        3.125,
        2.31,
        3.45,
        4.125,
        3.06,
        1.98,
        4.85
      ],
      "recommendations": [
        {
          "level": "watch",
          "text": "Up 78% \u2014 profit-target zone. A trailing exit (e.g., give back no more than a third) protects gains."
        },
        {
          "level": "warn",
          "text": "1 DTE \u2014 final-week gamma/theta zone. Close or roll unless you want an expiration outcome."
        },
        {
          "level": "warn",
          "text": "Underlying is below its 50-day SMA \u2014 intermediate trend is down; bullish premium is fighting the tape."
        }
      ],
      "notes": ""
    },
    {
      "id": "SAM1-JD-26C-0717-0702",
      "symbol": "JD",
      "strategy": "long_call",
      "strategy_label": "Long Call",
      "group": "1 Samurai Scan First",
      "buy_date": "2026-07-02",
      "expiration": "2026-07-17",
      "dte": 1,
      "contracts": 1,
      "legs": [
        {
          "type": "call",
          "side": "long",
          "strike": 26.0,
          "qty": 1
        }
      ],
      "entry_price": 1.2,
      "mark": 3.675,
      "pl": 247.5,
      "pl_pct": 206.2,
      "technicals": {
        "price": 29.68,
        "rsi": 65.4,
        "sma20": 27.09,
        "sma50": 28.91,
        "macd_hist": 0.492
      },
      "sparkline": [
        1.2,
        1.225,
        1.035,
        1.72,
        1.93,
        2.215,
        2.675,
        2.93,
        3.35,
        3.675
      ],
      "recommendations": [
        {
          "level": "action",
          "text": "Up 206% \u2014 consider taking profit or selling half to lock in the original debit."
        },
        {
          "level": "warn",
          "text": "1 DTE \u2014 final-week gamma/theta zone. Close or roll unless you want an expiration outcome."
        }
      ],
      "notes": ""
    },
    {
      "id": "SAM1-NEE-87_5C-0717-0702",
      "symbol": "NEE",
      "strategy": "long_call",
      "strategy_label": "Long Call",
      "group": "1 Samurai Scan First",
      "buy_date": "2026-07-02",
      "expiration": "2026-07-17",
      "dte": 1,
      "contracts": 1,
      "legs": [
        {
          "type": "call",
          "side": "long",
          "strike": 87.5,
          "qty": 1
        }
      ],
      "entry_price": 2.13,
      "mark": 1.97,
      "pl": -16.0,
      "pl_pct": -7.5,
      "technicals": {
        "price": 89.35,
        "rsi": 56.5,
        "sma20": 87.74,
        "sma50": 88.47,
        "macd_hist": 0.31
      },
      "sparkline": [
        2.13,
        1.535,
        2.145,
        1.325,
        1.03,
        1.165,
        1.415,
        2.295,
        1.67,
        1.97
      ],
      "recommendations": [
        {
          "level": "warn",
          "text": "1 DTE and underwater \u2014 time decay steepens from here; the probability of recovery drops sharply."
        }
      ],
      "notes": ""
    },
    {
      "id": "SAM1-XOM-137C-0717-0702",
      "symbol": "XOM",
      "strategy": "long_call",
      "strategy_label": "Long Call",
      "group": "1 Samurai Scan First",
      "buy_date": "2026-07-02",
      "expiration": "2026-07-17",
      "dte": 1,
      "contracts": 1,
      "legs": [
        {
          "type": "call",
          "side": "long",
          "strike": 137.0,
          "qty": 1
        }
      ],
      "entry_price": 3.07,
      "mark": 9.125,
      "pl": 605.5,
      "pl_pct": 197.2,
      "technicals": {
        "price": 145.95,
        "rsi": 57.1,
        "sma20": 139.48,
        "sma50": 146.13,
        "macd_hist": 1.394
      },
      "sparkline": [
        3.065,
        2.4,
        5.775,
        4.775,
        2.335,
        2.98,
        8.025,
        8.0,
        7.475,
        9.125
      ],
      "recommendations": [
        {
          "level": "action",
          "text": "Up 197% \u2014 consider taking profit or selling half to lock in the original debit."
        },
        {
          "level": "warn",
          "text": "1 DTE \u2014 final-week gamma/theta zone. Close or roll unless you want an expiration outcome."
        },
        {
          "level": "warn",
          "text": "Underlying is below its 50-day SMA \u2014 intermediate trend is down; bullish premium is fighting the tape."
        }
      ],
      "notes": ""
    },
    {
      "id": "SAM1-IOT-36C-0717-0702",
      "symbol": "IOT",
      "strategy": "long_call",
      "strategy_label": "Long Call",
      "group": "1 Samurai Scan First",
      "buy_date": "2026-07-02",
      "expiration": "2026-07-17",
      "dte": 1,
      "contracts": 1,
      "legs": [
        {
          "type": "call",
          "side": "long",
          "strike": 36.0,
          "qty": 1
        }
      ],
      "entry_price": 1.7,
      "mark": 1.65,
      "pl": -5.0,
      "pl_pct": -2.9,
      "technicals": {
        "price": 37.46,
        "rsi": 63.7,
        "sma20": 34.17,
        "sma50": 32.8,
        "macd_hist": 0.257
      },
      "sparkline": [
        1.7,
        2.6,
        1.75,
        1.725,
        1.875,
        1.625,
        1.5,
        1.725,
        1.1,
        1.65
      ],
      "recommendations": [
        {
          "level": "warn",
          "text": "1 DTE and underwater \u2014 time decay steepens from here; the probability of recovery drops sharply."
        }
      ],
      "notes": ""
    },
    {
      "id": "SAM1-NKE-44C-0717-0702",
      "symbol": "NKE",
      "strategy": "long_call",
      "strategy_label": "Long Call",
      "group": "1 Samurai Scan First",
      "buy_date": "2026-07-02",
      "expiration": "2026-07-17",
      "dte": 1,
      "contracts": 1,
      "legs": [
        {
          "type": "call",
          "side": "long",
          "strike": 44.0,
          "qty": 1
        }
      ],
      "entry_price": 1.35,
      "mark": 0.695,
      "pl": -65.5,
      "pl_pct": -48.5,
      "technicals": {
        "price": 44.57,
        "rsi": 55.4,
        "sma20": 42.93,
        "sma50": 43.61,
        "macd_hist": 0.197
      },
      "sparkline": [
        1.345,
        0.82,
        0.69,
        0.535,
        0.39,
        1.005,
        0.59,
        0.215,
        0.12,
        0.695
      ],
      "recommendations": [
        {
          "level": "warn",
          "text": "1 DTE and underwater \u2014 time decay steepens from here; the probability of recovery drops sharply."
        }
      ],
      "notes": ""
    },
    {
      "id": "SAM1-BAC-58C-0724-0702",
      "symbol": "BAC",
      "strategy": "long_call",
      "strategy_label": "Long Call",
      "group": "1 Samurai Scan First",
      "buy_date": "2026-07-02",
      "expiration": "2026-07-24",
      "dte": 8,
      "contracts": 1,
      "legs": [
        {
          "type": "call",
          "side": "long",
          "strike": 58.0,
          "qty": 1
        }
      ],
      "entry_price": 1.95,
      "mark": 3.575,
      "pl": 162.5,
      "pl_pct": 83.3,
      "technicals": {
        "price": 61.49,
        "rsi": 72.1,
        "sma20": 58.7,
        "sma50": 54.95,
        "macd_hist": 0.119
      },
      "sparkline": [
        1.945,
        2.725,
        2.65,
        1.63,
        2.09,
        2.315,
        2.24,
        2.9,
        3.725,
        3.575
      ],
      "recommendations": [
        {
          "level": "watch",
          "text": "Up 83% \u2014 profit-target zone. A trailing exit (e.g., give back no more than a third) protects gains."
        },
        {
          "level": "watch",
          "text": "RSI 72 (overbought) \u2014 momentum stretched; a scale-out here often beats waiting for the pullback."
        }
      ],
      "notes": ""
    },
    {
      "id": "GGPE-NVDA-170C-0807",
      "symbol": "NVDA",
      "strategy": "long_call",
      "strategy_label": "Long Call",
      "group": "GG_Positive Expectancy",
      "buy_date": "2026-07-01",
      "expiration": "2026-08-07",
      "dte": 22,
      "contracts": 1,
      "legs": [
        {
          "type": "call",
          "side": "long",
          "strike": 170.0,
          "qty": 1
        }
      ],
      "entry_price": 30.1,
      "mark": 37.775,
      "pl": 767.5,
      "pl_pct": 25.5,
      "technicals": {
        "price": 207.4,
        "rsi": 52.1,
        "sma20": 202.22,
        "sma50": 209.79,
        "macd_hist": 1.7
      },
      "sparkline": [
        27.375,
        27.375,
        27.95,
        29.125,
        36.175,
        34.525,
        41.85,
        34.975,
        42.8,
        42.425,
        37.775
      ],
      "recommendations": [
        {
          "level": "warn",
          "text": "Underlying is below its 50-day SMA \u2014 intermediate trend is down; bullish premium is fighting the tape."
        }
      ],
      "notes": ""
    },
    {
      "id": "GGPE-TSLA-375C-0807",
      "symbol": "TSLA",
      "strategy": "long_call",
      "strategy_label": "Long Call",
      "group": "GG_Positive Expectancy",
      "buy_date": "2026-07-01",
      "expiration": "2026-08-07",
      "dte": 22,
      "contracts": 1,
      "legs": [
        {
          "type": "call",
          "side": "long",
          "strike": 375.0,
          "qty": 1
        }
      ],
      "entry_price": 58.63,
      "mark": 29.0,
      "pl": -2963.0,
      "pl_pct": -50.5,
      "technicals": {
        "price": 391.06,
        "rsi": 46.0,
        "sma20": 398.63,
        "sma50": 409.97,
        "macd_hist": -0.818
      },
      "sparkline": [
        33.7,
        33.7,
        53.2,
        40.125,
        33.55,
        41.65,
        42.1,
        32.15,
        32.925,
        31.675,
        29.0
      ],
      "recommendations": [
        {
          "level": "action",
          "text": "Down 51% \u2014 standard long-premium stop is \u221250%; theta will keep working against the position."
        },
        {
          "level": "warn",
          "text": "Underlying closed below its 20-day SMA \u2014 short-term trend no longer supports the bullish thesis."
        },
        {
          "level": "warn",
          "text": "Underlying is below its 50-day SMA \u2014 intermediate trend is down; bullish premium is fighting the tape."
        },
        {
          "level": "watch",
          "text": "MACD histogram negative \u2014 bullish momentum fading on the daily chart."
        }
      ],
      "notes": ""
    },
    {
      "id": "GGHRS-TGT-120C-0807",
      "symbol": "TGT",
      "strategy": "long_call",
      "strategy_label": "Long Call",
      "group": "GG_High Relative Strength",
      "buy_date": "2026-07-01",
      "expiration": "2026-08-07",
      "dte": 22,
      "contracts": 1,
      "legs": [
        {
          "type": "call",
          "side": "long",
          "strike": 120.0,
          "qty": 1
        }
      ],
      "entry_price": 12.3,
      "mark": 20.6,
      "pl": 830.0,
      "pl_pct": 67.5,
      "technicals": {
        "price": 140.21,
        "rsi": 62.8,
        "sma20": 133.47,
        "sma50": 129.0,
        "macd_hist": 0.517
      },
      "sparkline": [
        12.325,
        12.325,
        8.95,
        9.675,
        13.875,
        13.575,
        16.025,
        15.775,
        14.85,
        18.8,
        20.6
      ],
      "recommendations": [
        {
          "level": "watch",
          "text": "Up 67% \u2014 profit-target zone. A trailing exit (e.g., give back no more than a third) protects gains."
        }
      ],
      "notes": ""
    },
    {
      "id": "GGHRS-AAP-54C-0807",
      "symbol": "AAP",
      "strategy": "long_call",
      "strategy_label": "Long Call",
      "group": "GG_High Relative Strength",
      "buy_date": "2026-07-01",
      "expiration": "2026-08-07",
      "dte": 22,
      "contracts": 1,
      "legs": [
        {
          "type": "call",
          "side": "long",
          "strike": 54.0,
          "qty": 1
        }
      ],
      "entry_price": 10.0,
      "mark": 2.45,
      "pl": -755.0,
      "pl_pct": -75.5,
      "technicals": {
        "price": 53.13,
        "rsi": 41.1,
        "sma20": 57.6,
        "sma50": 56.8,
        "macd_hist": -0.794
      },
      "sparkline": [
        8.75,
        4.9,
        4.65,
        3.95,
        4.7,
        5.7,
        4.05,
        4.05,
        2.375,
        2.45
      ],
      "recommendations": [
        {
          "level": "action",
          "text": "Down 76% \u2014 standard long-premium stop is \u221250%; theta will keep working against the position."
        },
        {
          "level": "warn",
          "text": "Underlying closed below its 20-day SMA \u2014 short-term trend no longer supports the bullish thesis."
        },
        {
          "level": "warn",
          "text": "Underlying is below its 50-day SMA \u2014 intermediate trend is down; bullish premium is fighting the tape."
        },
        {
          "level": "watch",
          "text": "MACD histogram negative \u2014 bullish momentum fading on the daily chart."
        }
      ],
      "notes": ""
    },
    {
      "id": "GGHRS-DLTR-109C-0807",
      "symbol": "DLTR",
      "strategy": "long_call",
      "strategy_label": "Long Call",
      "group": "GG_High Relative Strength",
      "buy_date": "2026-07-01",
      "expiration": "2026-08-07",
      "dte": 22,
      "contracts": 1,
      "legs": [
        {
          "type": "call",
          "side": "long",
          "strike": 109.0,
          "qty": 1
        }
      ],
      "entry_price": 14.08,
      "mark": 20.15,
      "pl": 607.0,
      "pl_pct": 43.1,
      "technicals": {
        "price": 128.45,
        "rsi": 65.6,
        "sma20": 120.78,
        "sma50": 109.22,
        "macd_hist": 0.078
      },
      "sparkline": [
        16.95,
        16.95,
        14.375,
        15.475,
        16.25,
        13.875,
        17.15,
        18.65,
        16.55,
        18.65,
        20.15
      ],
      "recommendations": [
        {
          "level": "hold",
          "text": "No exit triggers hit \u2014 thesis intact, time remaining, technicals aligned. Hold per plan."
        }
      ],
      "notes": ""
    },
    {
      "id": "GGPE-NVDA-170C-0807-0702",
      "symbol": "NVDA",
      "strategy": "long_call",
      "strategy_label": "Long Call",
      "group": "GG_Positive Expectancy",
      "buy_date": "2026-07-02",
      "expiration": "2026-08-07",
      "dte": 22,
      "contracts": 1,
      "legs": [
        {
          "type": "call",
          "side": "long",
          "strike": 170.0,
          "qty": 1
        }
      ],
      "entry_price": 27.38,
      "mark": 37.775,
      "pl": 1039.5,
      "pl_pct": 38.0,
      "technicals": {
        "price": 207.4,
        "rsi": 52.1,
        "sma20": 202.22,
        "sma50": 209.79,
        "macd_hist": 1.7
      },
      "sparkline": [
        27.375,
        27.95,
        29.125,
        36.175,
        34.525,
        41.85,
        34.975,
        42.8,
        42.425,
        37.775
      ],
      "recommendations": [
        {
          "level": "warn",
          "text": "Underlying is below its 50-day SMA \u2014 intermediate trend is down; bullish premium is fighting the tape."
        }
      ],
      "notes": ""
    },
    {
      "id": "GGHRS-AAP-51C-0807-0702",
      "symbol": "AAP",
      "strategy": "long_call",
      "strategy_label": "Long Call",
      "group": "GG_High Relative Strength",
      "buy_date": "2026-07-02",
      "expiration": "2026-08-07",
      "dte": 22,
      "contracts": 1,
      "legs": [
        {
          "type": "call",
          "side": "long",
          "strike": 51.0,
          "qty": 1
        }
      ],
      "entry_price": 11.45,
      "mark": 4.05,
      "pl": -740.0,
      "pl_pct": -64.6,
      "technicals": {
        "price": 53.13,
        "rsi": 41.1,
        "sma20": 57.6,
        "sma50": 56.8,
        "macd_hist": -0.794
      },
      "sparkline": [
        11.45,
        7.25,
        6.95,
        5.75,
        5.9,
        8.0,
        6.4,
        6.05,
        3.65,
        4.05
      ],
      "recommendations": [
        {
          "level": "action",
          "text": "Down 65% \u2014 standard long-premium stop is \u221250%; theta will keep working against the position."
        },
        {
          "level": "warn",
          "text": "Underlying closed below its 20-day SMA \u2014 short-term trend no longer supports the bullish thesis."
        },
        {
          "level": "warn",
          "text": "Underlying is below its 50-day SMA \u2014 intermediate trend is down; bullish premium is fighting the tape."
        },
        {
          "level": "watch",
          "text": "MACD histogram negative \u2014 bullish momentum fading on the daily chart."
        }
      ],
      "notes": ""
    },
    {
      "id": "GGHRS-DLTR-109C-0807-0702",
      "symbol": "DLTR",
      "strategy": "long_call",
      "strategy_label": "Long Call",
      "group": "GG_High Relative Strength",
      "buy_date": "2026-07-02",
      "expiration": "2026-08-07",
      "dte": 22,
      "contracts": 1,
      "legs": [
        {
          "type": "call",
          "side": "long",
          "strike": 109.0,
          "qty": 1
        }
      ],
      "entry_price": 16.95,
      "mark": 20.15,
      "pl": 320.0,
      "pl_pct": 18.9,
      "technicals": {
        "price": 128.45,
        "rsi": 65.6,
        "sma20": 120.78,
        "sma50": 109.22,
        "macd_hist": 0.078
      },
      "sparkline": [
        16.95,
        14.375,
        15.475,
        16.25,
        13.875,
        17.15,
        18.65,
        16.55,
        18.65,
        20.15
      ],
      "recommendations": [
        {
          "level": "hold",
          "text": "No exit triggers hit \u2014 thesis intact, time remaining, technicals aligned. Hold per plan."
        }
      ],
      "notes": ""
    },
    {
      "id": "GGPE-ASML-1480C-0821",
      "symbol": "ASML",
      "strategy": "long_call",
      "strategy_label": "Long Call",
      "group": "GG_Positive Expectancy",
      "buy_date": "2026-07-01",
      "expiration": "2026-08-21",
      "dte": 36,
      "contracts": 1,
      "legs": [
        {
          "type": "call",
          "side": "long",
          "strike": 1480.0,
          "qty": 1
        }
      ],
      "entry_price": 408.85,
      "mark": 332.25,
      "pl": -7660.0,
      "pl_pct": -18.7,
      "technicals": {
        "price": 1784.87,
        "rsi": 50.5,
        "sma20": 1821.65,
        "sma50": 1712.39,
        "macd_hist": -14.174
      },
      "sparkline": [
        349.75,
        349.75,
        391.05,
        325.3,
        342.45,
        368.3,
        358.35,
        297.2,
        337.6,
        367.25,
        332.25
      ],
      "recommendations": [
        {
          "level": "warn",
          "text": "Underlying closed below its 20-day SMA \u2014 short-term trend no longer supports the bullish thesis."
        },
        {
          "level": "watch",
          "text": "MACD histogram negative \u2014 bullish momentum fading on the daily chart."
        }
      ],
      "notes": ""
    },
    {
      "id": "GGPE-CMG-30C-0821",
      "symbol": "CMG",
      "strategy": "long_call",
      "strategy_label": "Long Call",
      "group": "GG_Positive Expectancy",
      "buy_date": "2026-07-01",
      "expiration": "2026-08-21",
      "dte": 36,
      "contracts": 1,
      "legs": [
        {
          "type": "call",
          "side": "long",
          "strike": 30.0,
          "qty": 1
        }
      ],
      "entry_price": 5.58,
      "mark": 4.9,
      "pl": -68.0,
      "pl_pct": -12.2,
      "technicals": {
        "price": 34.2,
        "rsi": 52.7,
        "sma20": 33.7,
        "sma50": 32.51,
        "macd_hist": 0.084
      },
      "sparkline": [
        5.9,
        5.9,
        4.86,
        5.1,
        4.35,
        5.225,
        5.85,
        6.925,
        6.9,
        5.6,
        4.9
      ],
      "recommendations": [
        {
          "level": "hold",
          "text": "No exit triggers hit \u2014 thesis intact, time remaining, technicals aligned. Hold per plan."
        }
      ],
      "notes": ""
    },
    {
      "id": "GGPE-GEV-880C-0821",
      "symbol": "GEV",
      "strategy": "long_call",
      "strategy_label": "Long Call",
      "group": "GG_Positive Expectancy",
      "buy_date": "2026-07-01",
      "expiration": "2026-08-21",
      "dte": 36,
      "contracts": 1,
      "legs": [
        {
          "type": "call",
          "side": "long",
          "strike": 880.0,
          "qty": 1
        }
      ],
      "entry_price": 279.25,
      "mark": 183.7,
      "pl": -9555.0,
      "pl_pct": -34.2,
      "technicals": {
        "price": 1036.22,
        "rsi": 47.4,
        "sma20": 1085.07,
        "sma50": 1037.05,
        "macd_hist": -9.125
      },
      "sparkline": [
        263.1,
        263.1,
        295.25,
        229.6,
        221.95,
        221.9,
        234.25,
        191.9,
        213.3,
        201.1,
        183.7
      ],
      "recommendations": [
        {
          "level": "warn",
          "text": "Underlying closed below its 20-day SMA \u2014 short-term trend no longer supports the bullish thesis."
        },
        {
          "level": "warn",
          "text": "Underlying is below its 50-day SMA \u2014 intermediate trend is down; bullish premium is fighting the tape."
        },
        {
          "level": "watch",
          "text": "MACD histogram negative \u2014 bullish momentum fading on the daily chart."
        }
      ],
      "notes": ""
    },
    {
      "id": "GGHRS-HPQ-19C-0821",
      "symbol": "HPQ",
      "strategy": "long_call",
      "strategy_label": "Long Call",
      "group": "GG_High Relative Strength",
      "buy_date": "2026-07-01",
      "expiration": "2026-08-21",
      "dte": 36,
      "contracts": 1,
      "legs": [
        {
          "type": "call",
          "side": "long",
          "strike": 19.0,
          "qty": 1
        }
      ],
      "entry_price": 3.55,
      "mark": 5.125,
      "pl": 157.5,
      "pl_pct": 44.4,
      "technicals": {
        "price": 24.14,
        "rsi": 54.1,
        "sma20": 23.32,
        "sma50": 23.57,
        "macd_hist": 0.135
      },
      "sparkline": [
        3.4,
        3.4,
        3.825,
        4.275,
        4.85,
        5.375,
        5.625,
        5.65,
        5.95,
        5.2,
        5.125
      ],
      "recommendations": [
        {
          "level": "hold",
          "text": "No exit triggers hit \u2014 thesis intact, time remaining, technicals aligned. Hold per plan."
        }
      ],
      "notes": ""
    },
    {
      "id": "GGHRS-WYNN-85C-0821",
      "symbol": "WYNN",
      "strategy": "long_call",
      "strategy_label": "Long Call",
      "group": "GG_High Relative Strength",
      "buy_date": "2026-07-01",
      "expiration": "2026-08-21",
      "dte": 36,
      "contracts": 1,
      "legs": [
        {
          "type": "call",
          "side": "long",
          "strike": 85.0,
          "qty": 1
        }
      ],
      "entry_price": 13.38,
      "mark": 14.85,
      "pl": 147.0,
      "pl_pct": 11.0,
      "technicals": {
        "price": 98.11,
        "rsi": 45.8,
        "sma20": 99.23,
        "sma50": 100.88,
        "macd_hist": -0.042
      },
      "sparkline": [
        13.225,
        13.225,
        13.125,
        13.125,
        14.05,
        15.6,
        16.025,
        14.225,
        12.925,
        13.325,
        14.85
      ],
      "recommendations": [
        {
          "level": "warn",
          "text": "Underlying closed below its 20-day SMA \u2014 short-term trend no longer supports the bullish thesis."
        },
        {
          "level": "warn",
          "text": "Underlying is below its 50-day SMA \u2014 intermediate trend is down; bullish premium is fighting the tape."
        },
        {
          "level": "watch",
          "text": "MACD histogram negative \u2014 bullish momentum fading on the daily chart."
        }
      ],
      "notes": ""
    },
    {
      "id": "GGHRS-M-20C-0821",
      "symbol": "M",
      "strategy": "long_call",
      "strategy_label": "Long Call",
      "group": "GG_High Relative Strength",
      "buy_date": "2026-07-01",
      "expiration": "2026-08-21",
      "dte": 36,
      "contracts": 1,
      "legs": [
        {
          "type": "call",
          "side": "long",
          "strike": 20.0,
          "qty": 1
        }
      ],
      "entry_price": 4.33,
      "mark": 4.175,
      "pl": -15.5,
      "pl_pct": -3.6,
      "technicals": {
        "price": 24.12,
        "rsi": 57.1,
        "sma20": 23.85,
        "sma50": 22.22,
        "macd_hist": -0.132
      },
      "sparkline": [
        3.575,
        3.575,
        4.05,
        3.975,
        3.22,
        3.25,
        3.205,
        3.3,
        3.285,
        3.7,
        4.175
      ],
      "recommendations": [
        {
          "level": "watch",
          "text": "MACD histogram negative \u2014 bullish momentum fading on the daily chart."
        }
      ],
      "notes": ""
    },
    {
      "id": "GGHRS-SWK-72_5C-0821",
      "symbol": "SWK",
      "strategy": "long_call",
      "strategy_label": "Long Call",
      "group": "GG_High Relative Strength",
      "buy_date": "2026-07-01",
      "expiration": "2026-08-21",
      "dte": 36,
      "contracts": 1,
      "legs": [
        {
          "type": "call",
          "side": "long",
          "strike": 72.5,
          "qty": 1
        }
      ],
      "entry_price": 20.7,
      "mark": 18.95,
      "pl": -175.0,
      "pl_pct": -8.5,
      "technicals": {
        "price": 91.31,
        "rsi": 59.8,
        "sma20": 89.03,
        "sma50": 82.94,
        "macd_hist": -0.52
      },
      "sparkline": [
        19.45,
        19.45,
        20.7,
        18.6,
        14.85,
        15.95,
        16.75,
        15.0,
        16.1,
        16.1,
        18.95
      ],
      "recommendations": [
        {
          "level": "watch",
          "text": "MACD histogram negative \u2014 bullish momentum fading on the daily chart."
        }
      ],
      "notes": ""
    },
    {
      "id": "GGHRS-MPLX-50C-0821",
      "symbol": "MPLX",
      "strategy": "long_call",
      "strategy_label": "Long Call",
      "group": "GG_High Relative Strength",
      "buy_date": "2026-07-01",
      "expiration": "2026-08-21",
      "dte": 36,
      "contracts": 1,
      "legs": [
        {
          "type": "call",
          "side": "long",
          "strike": 50.0,
          "qty": 1
        }
      ],
      "entry_price": 6.25,
      "mark": 7.05,
      "pl": 80.0,
      "pl_pct": 12.8,
      "technicals": {
        "price": 57.17,
        "rsi": 54.8,
        "sma20": 56.76,
        "sma50": 56.06,
        "macd_hist": -0.03
      },
      "sparkline": [
        7.1,
        7.4,
        7.8,
        7.35,
        7.6,
        7.0,
        7.65,
        6.85,
        6.65,
        7.05
      ],
      "recommendations": [
        {
          "level": "watch",
          "text": "MACD histogram negative \u2014 bullish momentum fading on the daily chart."
        }
      ],
      "notes": ""
    },
    {
      "id": "GGHRS-IRDM-50C-0821",
      "symbol": "IRDM",
      "strategy": "long_call",
      "strategy_label": "Long Call",
      "group": "GG_High Relative Strength",
      "buy_date": "2026-07-01",
      "expiration": "2026-08-21",
      "dte": 36,
      "contracts": 1,
      "legs": [
        {
          "type": "call",
          "side": "long",
          "strike": 50.0,
          "qty": 1
        }
      ],
      "entry_price": 6.7,
      "mark": 1.15,
      "pl": -555.0,
      "pl_pct": -82.8,
      "technicals": {
        "price": 46.61,
        "rsi": 45.5,
        "sma20": 48.56,
        "sma50": 46.94,
        "macd_hist": -0.531
      },
      "sparkline": [
        4.95,
        4.95,
        4.4,
        3.5,
        2.925,
        3.05,
        2.825,
        2.025,
        2.1,
        1.95,
        1.15
      ],
      "recommendations": [
        {
          "level": "action",
          "text": "Down 83% \u2014 standard long-premium stop is \u221250%; theta will keep working against the position."
        },
        {
          "level": "warn",
          "text": "Underlying closed below its 20-day SMA \u2014 short-term trend no longer supports the bullish thesis."
        },
        {
          "level": "warn",
          "text": "Underlying is below its 50-day SMA \u2014 intermediate trend is down; bullish premium is fighting the tape."
        },
        {
          "level": "watch",
          "text": "MACD histogram negative \u2014 bullish momentum fading on the daily chart."
        }
      ],
      "notes": ""
    },
    {
      "id": "GGHRS-ROST-185C-0821",
      "symbol": "ROST",
      "strategy": "long_call",
      "strategy_label": "Long Call",
      "group": "GG_High Relative Strength",
      "buy_date": "2026-07-01",
      "expiration": "2026-08-21",
      "dte": 36,
      "contracts": 1,
      "legs": [
        {
          "type": "call",
          "side": "long",
          "strike": 185.0,
          "qty": 1
        }
      ],
      "entry_price": 30.4,
      "mark": 48.85,
      "pl": 1845.0,
      "pl_pct": 60.7,
      "technicals": {
        "price": 232.72,
        "rsi": 60.9,
        "sma20": 221.11,
        "sma50": 224.05,
        "macd_hist": 1.577
      },
      "sparkline": [
        45.05,
        31.15,
        29.35,
        31.65,
        34.45,
        37.3,
        39.7,
        35.85,
        37.65,
        42.25,
        48.85
      ],
      "recommendations": [
        {
          "level": "watch",
          "text": "Up 61% \u2014 profit-target zone. A trailing exit (e.g., give back no more than a third) protects gains."
        }
      ],
      "notes": ""
    },
    {
      "id": "GGHRS-FDX-280C-0821",
      "symbol": "FDX",
      "strategy": "long_call",
      "strategy_label": "Long Call",
      "group": "GG_High Relative Strength",
      "buy_date": "2026-07-01",
      "expiration": "2026-08-21",
      "dte": 36,
      "contracts": 1,
      "legs": [
        {
          "type": "call",
          "side": "long",
          "strike": 280.0,
          "qty": 1
        }
      ],
      "entry_price": 38.58,
      "mark": 41.2,
      "pl": 262.0,
      "pl_pct": 6.8,
      "technicals": {
        "price": 318.2,
        "rsi": 50.6,
        "sma20": 317.21,
        "sma50": 318.07,
        "macd_hist": -0.17
      },
      "sparkline": [
        37.8,
        37.8,
        35.0,
        37.225,
        34.475,
        36.05,
        38.425,
        37.0,
        36.375,
        36.6,
        41.2
      ],
      "recommendations": [
        {
          "level": "watch",
          "text": "MACD histogram negative \u2014 bullish momentum fading on the daily chart."
        }
      ],
      "notes": ""
    },
    {
      "id": "GGHRS-SJM-105C-0821",
      "symbol": "SJM",
      "strategy": "long_call",
      "strategy_label": "Long Call",
      "group": "GG_High Relative Strength",
      "buy_date": "2026-07-01",
      "expiration": "2026-08-21",
      "dte": 36,
      "contracts": 1,
      "legs": [
        {
          "type": "call",
          "side": "long",
          "strike": 105.0,
          "qty": 1
        }
      ],
      "entry_price": 11.5,
      "mark": 9.5,
      "pl": -200.0,
      "pl_pct": -17.4,
      "technicals": {
        "price": 113.97,
        "rsi": 56.6,
        "sma20": 112.14,
        "sma50": 107.28,
        "macd_hist": -0.645
      },
      "sparkline": [
        12.85,
        12.85,
        8.75,
        9.85,
        9.65,
        7.95,
        8.25,
        7.85,
        6.25,
        6.25,
        9.5
      ],
      "recommendations": [
        {
          "level": "watch",
          "text": "MACD histogram negative \u2014 bullish momentum fading on the daily chart."
        }
      ],
      "notes": ""
    },
    {
      "id": "GGHRS-ALL-220C-0821",
      "symbol": "ALL",
      "strategy": "long_call",
      "strategy_label": "Long Call",
      "group": "GG_High Relative Strength",
      "buy_date": "2026-07-01",
      "expiration": "2026-08-21",
      "dte": 36,
      "contracts": 1,
      "legs": [
        {
          "type": "call",
          "side": "long",
          "strike": 220.0,
          "qty": 1
        }
      ],
      "entry_price": 27.15,
      "mark": 24.25,
      "pl": -290.0,
      "pl_pct": -10.7,
      "technicals": {
        "price": 241.86,
        "rsi": 54.3,
        "sma20": 240.69,
        "sma50": 225.78,
        "macd_hist": -0.931
      },
      "sparkline": [
        32.15,
        32.15,
        30.85,
        34.3,
        33.8,
        31.45,
        33.3,
        37.8,
        32.5,
        22.55,
        24.25
      ],
      "recommendations": [
        {
          "level": "watch",
          "text": "MACD histogram negative \u2014 bullish momentum fading on the daily chart."
        }
      ],
      "notes": ""
    },
    {
      "id": "GGHRS-TOL-135C-0821",
      "symbol": "TOL",
      "strategy": "long_call",
      "strategy_label": "Long Call",
      "group": "GG_High Relative Strength",
      "buy_date": "2026-07-01",
      "expiration": "2026-08-21",
      "dte": 36,
      "contracts": 1,
      "legs": [
        {
          "type": "call",
          "side": "long",
          "strike": 135.0,
          "qty": 1
        }
      ],
      "entry_price": 25.45,
      "mark": 21.7,
      "pl": -375.0,
      "pl_pct": -14.7,
      "technicals": {
        "price": 155.81,
        "rsi": 56.5,
        "sma20": 154.96,
        "sma50": 144.68,
        "macd_hist": -0.868
      },
      "sparkline": [
        23.8,
        23.8,
        22.2,
        19.6,
        14.75,
        16.65,
        17.9,
        16.0,
        19.5,
        20.65,
        21.7
      ],
      "recommendations": [
        {
          "level": "watch",
          "text": "MACD histogram negative \u2014 bullish momentum fading on the daily chart."
        }
      ],
      "notes": ""
    },
    {
      "id": "GGHRS-WSM-200C-0821",
      "symbol": "WSM",
      "strategy": "long_call",
      "strategy_label": "Long Call",
      "group": "GG_High Relative Strength",
      "buy_date": "2026-07-01",
      "expiration": "2026-08-21",
      "dte": 36,
      "contracts": 1,
      "legs": [
        {
          "type": "call",
          "side": "long",
          "strike": 200.0,
          "qty": 1
        }
      ],
      "entry_price": 32.4,
      "mark": 30.15,
      "pl": -225.0,
      "pl_pct": -6.9,
      "technicals": {
        "price": 228.38,
        "rsi": 58.5,
        "sma20": 226.93,
        "sma50": 207.89,
        "macd_hist": -1.728
      },
      "sparkline": [
        30.7,
        30.7,
        28.6,
        26.35,
        23.45,
        24.65,
        26.0,
        21.4,
        24.5,
        25.75,
        30.15
      ],
      "recommendations": [
        {
          "level": "watch",
          "text": "MACD histogram negative \u2014 bullish momentum fading on the daily chart."
        }
      ],
      "notes": ""
    },
    {
      "id": "GGHRS-OZK-47_5C-0821",
      "symbol": "OZK",
      "strategy": "long_call",
      "strategy_label": "Long Call",
      "group": "GG_High Relative Strength",
      "buy_date": "2026-07-01",
      "expiration": "2026-08-21",
      "dte": 36,
      "contracts": 1,
      "legs": [
        {
          "type": "call",
          "side": "long",
          "strike": 47.5,
          "qty": 1
        }
      ],
      "entry_price": 5.9,
      "mark": 6.35,
      "pl": 45.0,
      "pl_pct": 7.6,
      "technicals": {
        "price": 53.09,
        "rsi": 64.3,
        "sma20": 50.78,
        "sma50": 49.54,
        "macd_hist": 0.07
      },
      "sparkline": [
        3.55,
        3.55,
        3.25,
        3.625,
        3.0,
        3.85,
        3.8,
        4.2,
        4.35,
        4.85,
        6.35
      ],
      "recommendations": [
        {
          "level": "hold",
          "text": "No exit triggers hit \u2014 thesis intact, time remaining, technicals aligned. Hold per plan."
        }
      ],
      "notes": ""
    },
    {
      "id": "GGCL-OKLO-40C-0821",
      "symbol": "OKLO",
      "strategy": "long_call",
      "strategy_label": "Long Call",
      "group": "GG_Core Leadership",
      "buy_date": "2026-07-01",
      "expiration": "2026-08-21",
      "dte": 36,
      "contracts": 1,
      "legs": [
        {
          "type": "call",
          "side": "long",
          "strike": 40.0,
          "qty": 1
        }
      ],
      "entry_price": 14.4,
      "mark": 5.8,
      "pl": -860.0,
      "pl_pct": -59.7,
      "technicals": {
        "price": 41.7,
        "rsi": 29.4,
        "sma20": 51.26,
        "sma50": 59.6,
        "macd_hist": -0.487
      },
      "sparkline": [
        13.9,
        13.9,
        14.025,
        10.6,
        10.2,
        11.725,
        10.85,
        8.575,
        9.25,
        8.2,
        5.8
      ],
      "recommendations": [
        {
          "level": "action",
          "text": "Down 60% \u2014 standard long-premium stop is \u221250%; theta will keep working against the position."
        },
        {
          "level": "warn",
          "text": "RSI 29 (oversold) \u2014 underlying momentum has broken down against the position."
        },
        {
          "level": "warn",
          "text": "Underlying closed below its 20-day SMA \u2014 short-term trend no longer supports the bullish thesis."
        },
        {
          "level": "warn",
          "text": "Underlying is below its 50-day SMA \u2014 intermediate trend is down; bullish premium is fighting the tape."
        },
        {
          "level": "watch",
          "text": "MACD histogram negative \u2014 bullish momentum fading on the daily chart."
        }
      ],
      "notes": ""
    },
    {
      "id": "SAM1-PDD-80C-0821",
      "symbol": "PDD",
      "strategy": "long_call",
      "strategy_label": "Long Call",
      "group": "1 Samurai Scan First",
      "buy_date": "2026-07-01",
      "expiration": "2026-08-21",
      "dte": 36,
      "contracts": 1,
      "legs": [
        {
          "type": "call",
          "side": "long",
          "strike": 80.0,
          "qty": 1
        }
      ],
      "entry_price": 6.65,
      "mark": 8.675,
      "pl": 202.5,
      "pl_pct": 30.5,
      "technicals": {
        "price": 86.68,
        "rsi": 57.7,
        "sma20": 81.02,
        "sma50": 86.9,
        "macd_hist": 1.155
      },
      "sparkline": [
        6.425,
        6.425,
        7.25,
        6.35,
        7.8,
        7.95,
        8.1,
        7.275,
        6.725,
        7.95,
        8.675
      ],
      "recommendations": [
        {
          "level": "warn",
          "text": "Underlying is below its 50-day SMA \u2014 intermediate trend is down; bullish premium is fighting the tape."
        }
      ],
      "notes": ""
    },
    {
      "id": "SAM1-WMT-110C-0821",
      "symbol": "WMT",
      "strategy": "long_call",
      "strategy_label": "Long Call",
      "group": "1 Samurai Scan First",
      "buy_date": "2026-07-01",
      "expiration": "2026-08-21",
      "dte": 36,
      "contracts": 1,
      "legs": [
        {
          "type": "call",
          "side": "long",
          "strike": 110.0,
          "qty": 1
        }
      ],
      "entry_price": 4.43,
      "mark": 7.475,
      "pl": 304.5,
      "pl_pct": 68.7,
      "technicals": {
        "price": 114.95,
        "rsi": 48.1,
        "sma20": 114.41,
        "sma50": 119.97,
        "macd_hist": 0.452
      },
      "sparkline": [
        5.975,
        5.975,
        5.25,
        5.675,
        6.575,
        5.925,
        6.825,
        7.65,
        6.6,
        5.85,
        7.475
      ],
      "recommendations": [
        {
          "level": "watch",
          "text": "Up 69% \u2014 profit-target zone. A trailing exit (e.g., give back no more than a third) protects gains."
        },
        {
          "level": "warn",
          "text": "Underlying is below its 50-day SMA \u2014 intermediate trend is down; bullish premium is fighting the tape."
        }
      ],
      "notes": ""
    },
    {
      "id": "GGPE-AMD-410C-0821-0702",
      "symbol": "AMD",
      "strategy": "long_call",
      "strategy_label": "Long Call",
      "group": "GG_Positive Expectancy",
      "buy_date": "2026-07-02",
      "expiration": "2026-08-21",
      "dte": 36,
      "contracts": 1,
      "legs": [
        {
          "type": "call",
          "side": "long",
          "strike": 410.0,
          "qty": 1
        }
      ],
      "entry_price": 127.1,
      "mark": 108.95,
      "pl": -1815.0,
      "pl_pct": -14.3,
      "technicals": {
        "price": 500.94,
        "rsi": 46.9,
        "sma20": 533.85,
        "sma50": 496.27,
        "macd_hist": -6.3
      },
      "sparkline": [
        127.1,
        157.275,
        124.25,
        125.7,
        150.05,
        159.475,
        137.925,
        150.1,
        133.125,
        108.95
      ],
      "recommendations": [
        {
          "level": "warn",
          "text": "Underlying closed below its 20-day SMA \u2014 short-term trend no longer supports the bullish thesis."
        },
        {
          "level": "watch",
          "text": "MACD histogram negative \u2014 bullish momentum fading on the daily chart."
        }
      ],
      "notes": ""
    },
    {
      "id": "GGPE-DASH-150C-0821-0702",
      "symbol": "DASH",
      "strategy": "long_call",
      "strategy_label": "Long Call",
      "group": "GG_Positive Expectancy",
      "buy_date": "2026-07-02",
      "expiration": "2026-08-21",
      "dte": 36,
      "contracts": 1,
      "legs": [
        {
          "type": "call",
          "side": "long",
          "strike": 150.0,
          "qty": 1
        }
      ],
      "entry_price": 44.83,
      "mark": 39.3,
      "pl": -553.0,
      "pl_pct": -12.3,
      "technicals": {
        "price": 186.36,
        "rsi": 56.2,
        "sma20": 184.12,
        "sma50": 168.94,
        "macd_hist": -0.575
      },
      "sparkline": [
        44.825,
        42.475,
        48.025,
        42.6,
        45.175,
        44.625,
        42.45,
        40.975,
        42.425,
        39.3
      ],
      "recommendations": [
        {
          "level": "watch",
          "text": "MACD histogram negative \u2014 bullish momentum fading on the daily chart."
        }
      ],
      "notes": ""
    },
    {
      "id": "GGPE-DELL-320C-0821-0702",
      "symbol": "DELL",
      "strategy": "long_call",
      "strategy_label": "Long Call",
      "group": "GG_Positive Expectancy",
      "buy_date": "2026-07-02",
      "expiration": "2026-08-21",
      "dte": 36,
      "contracts": 1,
      "legs": [
        {
          "type": "call",
          "side": "long",
          "strike": 320.0,
          "qty": 1
        }
      ],
      "entry_price": 91.25,
      "mark": 84.55,
      "pl": -670.0,
      "pl_pct": -7.3,
      "technicals": {
        "price": 391.38,
        "rsi": 47.2,
        "sma20": 420.94,
        "sma50": 361.77,
        "macd_hist": -6.342
      },
      "sparkline": [
        91.25,
        104.35,
        110.575,
        124.025,
        138.525,
        123.15,
        115.55,
        143.175,
        103.4,
        84.55
      ],
      "recommendations": [
        {
          "level": "warn",
          "text": "Underlying closed below its 20-day SMA \u2014 short-term trend no longer supports the bullish thesis."
        },
        {
          "level": "watch",
          "text": "MACD histogram negative \u2014 bullish momentum fading on the daily chart."
        }
      ],
      "notes": ""
    },
    {
      "id": "GGPE-HOOD-90C-0821-0702",
      "symbol": "HOOD",
      "strategy": "long_call",
      "strategy_label": "Long Call",
      "group": "GG_Positive Expectancy",
      "buy_date": "2026-07-02",
      "expiration": "2026-08-21",
      "dte": 36,
      "contracts": 1,
      "legs": [
        {
          "type": "call",
          "side": "long",
          "strike": 90.0,
          "qty": 1
        }
      ],
      "entry_price": 26.53,
      "mark": 20.0,
      "pl": -653.0,
      "pl_pct": -24.6,
      "technicals": {
        "price": 106.02,
        "rsi": 52.3,
        "sma20": 107.55,
        "sma50": 92.56,
        "macd_hist": -0.677
      },
      "sparkline": [
        26.525,
        30.45,
        26.325,
        26.55,
        27.95,
        25.175,
        22.975,
        26.05,
        27.625,
        20.0
      ],
      "recommendations": [
        {
          "level": "warn",
          "text": "Underlying closed below its 20-day SMA \u2014 short-term trend no longer supports the bullish thesis."
        },
        {
          "level": "watch",
          "text": "MACD histogram negative \u2014 bullish momentum fading on the daily chart."
        }
      ],
      "notes": ""
    },
    {
      "id": "GGPE-TSLA-320C-0821-0702",
      "symbol": "TSLA",
      "strategy": "long_call",
      "strategy_label": "Long Call",
      "group": "GG_Positive Expectancy",
      "buy_date": "2026-07-02",
      "expiration": "2026-08-21",
      "dte": 36,
      "contracts": 1,
      "legs": [
        {
          "type": "call",
          "side": "long",
          "strike": 320.0,
          "qty": 1
        }
      ],
      "entry_price": 79.3,
      "mark": 75.3,
      "pl": -400.0,
      "pl_pct": -5.0,
      "technicals": {
        "price": 391.06,
        "rsi": 46.0,
        "sma20": 398.63,
        "sma50": 409.97,
        "macd_hist": -0.818
      },
      "sparkline": [
        79.3,
        103.85,
        87.85,
        78.975,
        90.725,
        91.7,
        79.25,
        80.275,
        78.55,
        75.3
      ],
      "recommendations": [
        {
          "level": "warn",
          "text": "Underlying closed below its 20-day SMA \u2014 short-term trend no longer supports the bullish thesis."
        },
        {
          "level": "warn",
          "text": "Underlying is below its 50-day SMA \u2014 intermediate trend is down; bullish premium is fighting the tape."
        },
        {
          "level": "watch",
          "text": "MACD histogram negative \u2014 bullish momentum fading on the daily chart."
        }
      ],
      "notes": ""
    },
    {
      "id": "GGPE-TSM-350C-0821-0702",
      "symbol": "TSM",
      "strategy": "long_call",
      "strategy_label": "Long Call",
      "group": "GG_Positive Expectancy",
      "buy_date": "2026-07-02",
      "expiration": "2026-08-21",
      "dte": 36,
      "contracts": 1,
      "legs": [
        {
          "type": "call",
          "side": "long",
          "strike": 350.0,
          "qty": 1
        }
      ],
      "entry_price": 93.28,
      "mark": 67.525,
      "pl": -2575.5,
      "pl_pct": -27.6,
      "technicals": {
        "price": 409.74,
        "rsi": 42.4,
        "sma20": 439.06,
        "sma50": 425.57,
        "macd_hist": -4.957
      },
      "sparkline": [
        93.275,
        109.025,
        90.3,
        94.0,
        93.975,
        90.875,
        79.225,
        77.85,
        76.75,
        67.525
      ],
      "recommendations": [
        {
          "level": "warn",
          "text": "Underlying closed below its 20-day SMA \u2014 short-term trend no longer supports the bullish thesis."
        },
        {
          "level": "warn",
          "text": "Underlying is below its 50-day SMA \u2014 intermediate trend is down; bullish premium is fighting the tape."
        },
        {
          "level": "watch",
          "text": "MACD histogram negative \u2014 bullish momentum fading on the daily chart."
        }
      ],
      "notes": ""
    },
    {
      "id": "GGHRS-ALL-230C-0821-0702",
      "symbol": "ALL",
      "strategy": "long_call",
      "strategy_label": "Long Call",
      "group": "GG_High Relative Strength",
      "buy_date": "2026-07-02",
      "expiration": "2026-08-21",
      "dte": 36,
      "contracts": 1,
      "legs": [
        {
          "type": "call",
          "side": "long",
          "strike": 230.0,
          "qty": 1
        }
      ],
      "entry_price": 23.7,
      "mark": 16.45,
      "pl": -725.0,
      "pl_pct": -30.6,
      "technicals": {
        "price": 241.86,
        "rsi": 54.3,
        "sma20": 240.69,
        "sma50": 225.78,
        "macd_hist": -0.931
      },
      "sparkline": [
        23.7,
        22.3,
        25.7,
        24.85,
        22.7,
        25.15,
        28.85,
        24.2,
        14.85,
        16.45
      ],
      "recommendations": [
        {
          "level": "watch",
          "text": "MACD histogram negative \u2014 bullish momentum fading on the daily chart."
        }
      ],
      "notes": ""
    },
    {
      "id": "GGHRS-AMR-125C-0821-0702",
      "symbol": "AMR",
      "strategy": "long_call",
      "strategy_label": "Long Call",
      "group": "GG_High Relative Strength",
      "buy_date": "2026-07-02",
      "expiration": "2026-08-21",
      "dte": 36,
      "contracts": 1,
      "legs": [
        {
          "type": "call",
          "side": "long",
          "strike": 125.0,
          "qty": 1
        }
      ],
      "entry_price": 37.75,
      "mark": 24.65,
      "pl": -1310.0,
      "pl_pct": -34.7,
      "technicals": {
        "price": 145.22,
        "rsi": 32.5,
        "sma20": 161.1,
        "sma50": 180.22,
        "macd_hist": -0.35
      },
      "sparkline": [
        37.75,
        37.1,
        30.95,
        31.0,
        29.05,
        25.95,
        27.45,
        32.65,
        30.7,
        24.65
      ],
      "recommendations": [
        {
          "level": "warn",
          "text": "Underlying closed below its 20-day SMA \u2014 short-term trend no longer supports the bullish thesis."
        },
        {
          "level": "warn",
          "text": "Underlying is below its 50-day SMA \u2014 intermediate trend is down; bullish premium is fighting the tape."
        },
        {
          "level": "watch",
          "text": "MACD histogram negative \u2014 bullish momentum fading on the daily chart."
        }
      ],
      "notes": ""
    },
    {
      "id": "GGHRS-ANF-75C-0821-0702",
      "symbol": "ANF",
      "strategy": "long_call",
      "strategy_label": "Long Call",
      "group": "GG_High Relative Strength",
      "buy_date": "2026-07-02",
      "expiration": "2026-08-21",
      "dte": 36,
      "contracts": 1,
      "legs": [
        {
          "type": "call",
          "side": "long",
          "strike": 75.0,
          "qty": 1
        }
      ],
      "entry_price": 18.8,
      "mark": 23.8,
      "pl": 500.0,
      "pl_pct": 26.6,
      "technicals": {
        "price": 97.37,
        "rsi": 65.4,
        "sma20": 90.15,
        "sma50": 83.14,
        "macd_hist": 0.483
      },
      "sparkline": [
        18.8,
        16.85,
        16.15,
        14.15,
        15.8,
        19.0,
        18.5,
        18.75,
        23.4,
        23.8
      ],
      "recommendations": [
        {
          "level": "hold",
          "text": "No exit triggers hit \u2014 thesis intact, time remaining, technicals aligned. Hold per plan."
        }
      ],
      "notes": ""
    },
    {
      "id": "GGHRS-B-29C-0821-0702",
      "symbol": "B",
      "strategy": "long_call",
      "strategy_label": "Long Call",
      "group": "GG_High Relative Strength",
      "buy_date": "2026-07-02",
      "expiration": "2026-08-21",
      "dte": 36,
      "contracts": 1,
      "legs": [
        {
          "type": "call",
          "side": "long",
          "strike": 29.0,
          "qty": 1
        }
      ],
      "entry_price": 9.33,
      "mark": 6.4,
      "pl": -293.0,
      "pl_pct": -31.4,
      "technicals": {
        "price": 34.84,
        "rsi": 36.9,
        "sma20": 37.31,
        "sma50": 39.85,
        "macd_hist": -0.087
      },
      "sparkline": [
        9.325,
        9.575,
        8.7,
        6.95,
        7.925,
        7.975,
        7.3,
        8.15,
        7.325,
        6.4
      ],
      "recommendations": [
        {
          "level": "warn",
          "text": "Underlying closed below its 20-day SMA \u2014 short-term trend no longer supports the bullish thesis."
        },
        {
          "level": "warn",
          "text": "Underlying is below its 50-day SMA \u2014 intermediate trend is down; bullish premium is fighting the tape."
        },
        {
          "level": "watch",
          "text": "MACD histogram negative \u2014 bullish momentum fading on the daily chart."
        }
      ],
      "notes": ""
    },
    {
      "id": "GGHRS-BALL-57_5C-0821-0702",
      "symbol": "BALL",
      "strategy": "long_call",
      "strategy_label": "Long Call",
      "group": "GG_High Relative Strength",
      "buy_date": "2026-07-02",
      "expiration": "2026-08-21",
      "dte": 36,
      "contracts": 1,
      "legs": [
        {
          "type": "call",
          "side": "long",
          "strike": 57.5,
          "qty": 1
        }
      ],
      "entry_price": 6.75,
      "mark": 6.35,
      "pl": -40.0,
      "pl_pct": -5.9,
      "technicals": {
        "price": 63.15,
        "rsi": 63.4,
        "sma20": 61.11,
        "sma50": 57.99,
        "macd_hist": -0.096
      },
      "sparkline": [
        6.75,
        6.3,
        6.65,
        4.5,
        5.0,
        5.3,
        4.95,
        4.65,
        4.5,
        6.35
      ],
      "recommendations": [
        {
          "level": "watch",
          "text": "MACD histogram negative \u2014 bullish momentum fading on the daily chart."
        }
      ],
      "notes": ""
    },
    {
      "id": "GGHRS-BBY-67_5C-0821-0702",
      "symbol": "BBY",
      "strategy": "long_call",
      "strategy_label": "Long Call",
      "group": "GG_High Relative Strength",
      "buy_date": "2026-07-02",
      "expiration": "2026-08-21",
      "dte": 36,
      "contracts": 1,
      "legs": [
        {
          "type": "call",
          "side": "long",
          "strike": 67.5,
          "qty": 1
        }
      ],
      "entry_price": 10.9,
      "mark": 18.25,
      "pl": 735.0,
      "pl_pct": 67.4,
      "technicals": {
        "price": 85.29,
        "rsi": 71.4,
        "sma20": 78.64,
        "sma50": 71.34,
        "macd_hist": 0.408
      },
      "sparkline": [
        10.9,
        11.6,
        12.0,
        11.4,
        13.05,
        15.8,
        14.9,
        16.35,
        18.2,
        18.25
      ],
      "recommendations": [
        {
          "level": "watch",
          "text": "Up 67% \u2014 profit-target zone. A trailing exit (e.g., give back no more than a third) protects gains."
        },
        {
          "level": "watch",
          "text": "RSI 71 (overbought) \u2014 momentum stretched; a scale-out here often beats waiting for the pullback."
        }
      ],
      "notes": ""
    },
    {
      "id": "GGHRS-CASY-700C-0821-0702",
      "symbol": "CASY",
      "strategy": "long_call",
      "strategy_label": "Long Call",
      "group": "GG_High Relative Strength",
      "buy_date": "2026-07-02",
      "expiration": "2026-08-21",
      "dte": 36,
      "contracts": 1,
      "legs": [
        {
          "type": "call",
          "side": "long",
          "strike": 700.0,
          "qty": 1
        }
      ],
      "entry_price": 106.95,
      "mark": 131.55,
      "pl": 2460.0,
      "pl_pct": 23.0,
      "technicals": {
        "price": 827.04,
        "rsi": 51.7,
        "sma20": 815.7,
        "sma50": 824.7,
        "macd_hist": 2.09
      },
      "sparkline": [
        106.95,
        115.8,
        110.45,
        148.1,
        128.45,
        126.1,
        164.2,
        151.75,
        113.95,
        131.55
      ],
      "recommendations": [
        {
          "level": "hold",
          "text": "No exit triggers hit \u2014 thesis intact, time remaining, technicals aligned. Hold per plan."
        }
      ],
      "notes": ""
    },
    {
      "id": "GGHRS-CB-325C-0821-0702",
      "symbol": "CB",
      "strategy": "long_call",
      "strategy_label": "Long Call",
      "group": "GG_High Relative Strength",
      "buy_date": "2026-07-02",
      "expiration": "2026-08-21",
      "dte": 36,
      "contracts": 1,
      "legs": [
        {
          "type": "call",
          "side": "long",
          "strike": 325.0,
          "qty": 1
        }
      ],
      "entry_price": 39.7,
      "mark": 23.4,
      "pl": -1630.0,
      "pl_pct": -41.1,
      "technicals": {
        "price": 343.7,
        "rsi": 52.3,
        "sma20": 343.08,
        "sma50": 330.69,
        "macd_hist": -1.344
      },
      "sparkline": [
        39.7,
        35.25,
        37.9,
        34.5,
        27.35,
        27.05,
        33.45,
        26.25,
        18.6,
        23.4
      ],
      "recommendations": [
        {
          "level": "watch",
          "text": "MACD histogram negative \u2014 bullish momentum fading on the daily chart."
        }
      ],
      "notes": ""
    },
    {
      "id": "GGHRS-CINF-170C-0821-0702",
      "symbol": "CINF",
      "strategy": "long_call",
      "strategy_label": "Long Call",
      "group": "GG_High Relative Strength",
      "buy_date": "2026-07-02",
      "expiration": "2026-08-21",
      "dte": 36,
      "contracts": 1,
      "legs": [
        {
          "type": "call",
          "side": "long",
          "strike": 170.0,
          "qty": 1
        }
      ],
      "entry_price": 23.45,
      "mark": 10.35,
      "pl": -1310.0,
      "pl_pct": -55.9,
      "technicals": {
        "price": 176.29,
        "rsi": 49.2,
        "sma20": 180.35,
        "sma50": 170.62,
        "macd_hist": -1.625
      },
      "sparkline": [
        23.45,
        21.95,
        22.2,
        15.4,
        9.85,
        12.15,
        15.2,
        13.7,
        7.65,
        10.35
      ],
      "recommendations": [
        {
          "level": "action",
          "text": "Down 56% \u2014 standard long-premium stop is \u221250%; theta will keep working against the position."
        },
        {
          "level": "warn",
          "text": "Underlying closed below its 20-day SMA \u2014 short-term trend no longer supports the bullish thesis."
        },
        {
          "level": "watch",
          "text": "MACD histogram negative \u2014 bullish momentum fading on the daily chart."
        }
      ],
      "notes": ""
    },
    {
      "id": "GGHRS-CTVA-75C-0821-0702",
      "symbol": "CTVA",
      "strategy": "long_call",
      "strategy_label": "Long Call",
      "group": "GG_High Relative Strength",
      "buy_date": "2026-07-02",
      "expiration": "2026-08-21",
      "dte": 36,
      "contracts": 1,
      "legs": [
        {
          "type": "call",
          "side": "long",
          "strike": 75.0,
          "qty": 1
        }
      ],
      "entry_price": 11.35,
      "mark": 12.3,
      "pl": 95.0,
      "pl_pct": 8.4,
      "technicals": {
        "price": 86.65,
        "rsi": 64.0,
        "sma20": 83.28,
        "sma50": 80.75,
        "macd_hist": 0.126
      },
      "sparkline": [
        11.35,
        12.35,
        12.6,
        11.2,
        9.95,
        11.8,
        12.0,
        11.05,
        10.0,
        12.3
      ],
      "recommendations": [
        {
          "level": "hold",
          "text": "No exit triggers hit \u2014 thesis intact, time remaining, technicals aligned. Hold per plan."
        }
      ],
      "notes": ""
    },
    {
      "id": "GGHRS-DVN-30C-0821-0702",
      "symbol": "DVN",
      "strategy": "long_call",
      "strategy_label": "Long Call",
      "group": "GG_High Relative Strength",
      "buy_date": "2026-07-02",
      "expiration": "2026-08-21",
      "dte": 36,
      "contracts": 1,
      "legs": [
        {
          "type": "call",
          "side": "long",
          "strike": 30.0,
          "qty": 1
        }
      ],
      "entry_price": 10.85,
      "mark": 13.15,
      "pl": 230.0,
      "pl_pct": 21.2,
      "technicals": {
        "price": 43.03,
        "rsi": 49.3,
        "sma20": 42.31,
        "sma50": 44.65,
        "macd_hist": 0.333
      },
      "sparkline": [
        10.85,
        10.625,
        12.75,
        13.425,
        12.875,
        12.325,
        14.2,
        13.925,
        12.925,
        13.15
      ],
      "recommendations": [
        {
          "level": "warn",
          "text": "Underlying is below its 50-day SMA \u2014 intermediate trend is down; bullish premium is fighting the tape."
        }
      ],
      "notes": ""
    },
    {
      "id": "GGHRS-FANG-150C-0821-0702",
      "symbol": "FANG",
      "strategy": "long_call",
      "strategy_label": "Long Call",
      "group": "GG_High Relative Strength",
      "buy_date": "2026-07-02",
      "expiration": "2026-08-21",
      "dte": 36,
      "contracts": 1,
      "legs": [
        {
          "type": "call",
          "side": "long",
          "strike": 150.0,
          "qty": 1
        }
      ],
      "entry_price": 24.4,
      "mark": 41.0,
      "pl": 1660.0,
      "pl_pct": 68.0,
      "technicals": {
        "price": 190.13,
        "rsi": 54.3,
        "sma20": 182.97,
        "sma50": 191.81,
        "macd_hist": 1.926
      },
      "sparkline": [
        24.4,
        25.45,
        32.55,
        37.45,
        33.25,
        34.25,
        42.65,
        41.8,
        40.35,
        41.0
      ],
      "recommendations": [
        {
          "level": "watch",
          "text": "Up 68% \u2014 profit-target zone. A trailing exit (e.g., give back no more than a third) protects gains."
        },
        {
          "level": "warn",
          "text": "Underlying is below its 50-day SMA \u2014 intermediate trend is down; bullish premium is fighting the tape."
        }
      ],
      "notes": ""
    },
    {
      "id": "GGHRS-FDX-280C-0821-0702",
      "symbol": "FDX",
      "strategy": "long_call",
      "strategy_label": "Long Call",
      "group": "GG_High Relative Strength",
      "buy_date": "2026-07-02",
      "expiration": "2026-08-21",
      "dte": 36,
      "contracts": 1,
      "legs": [
        {
          "type": "call",
          "side": "long",
          "strike": 280.0,
          "qty": 1
        }
      ],
      "entry_price": 37.8,
      "mark": 41.2,
      "pl": 340.0,
      "pl_pct": 9.0,
      "technicals": {
        "price": 318.2,
        "rsi": 50.6,
        "sma20": 317.21,
        "sma50": 318.07,
        "macd_hist": -0.17
      },
      "sparkline": [
        37.8,
        35.0,
        37.225,
        34.475,
        36.05,
        38.425,
        37.0,
        36.375,
        36.6,
        41.2
      ],
      "recommendations": [
        {
          "level": "watch",
          "text": "MACD histogram negative \u2014 bullish momentum fading on the daily chart."
        }
      ],
      "notes": ""
    },
    {
      "id": "GGHRS-HPQ-18C-0821-0702",
      "symbol": "HPQ",
      "strategy": "long_call",
      "strategy_label": "Long Call",
      "group": "GG_High Relative Strength",
      "buy_date": "2026-07-02",
      "expiration": "2026-08-21",
      "dte": 36,
      "contracts": 1,
      "legs": [
        {
          "type": "call",
          "side": "long",
          "strike": 18.0,
          "qty": 1
        }
      ],
      "entry_price": 4.2,
      "mark": 6.175,
      "pl": 197.5,
      "pl_pct": 47.0,
      "technicals": {
        "price": 24.14,
        "rsi": 54.1,
        "sma20": 23.32,
        "sma50": 23.57,
        "macd_hist": 0.135
      },
      "sparkline": [
        4.2,
        4.575,
        5.2,
        5.65,
        6.35,
        6.6,
        6.65,
        6.35,
        6.1,
        6.175
      ],
      "recommendations": [
        {
          "level": "hold",
          "text": "No exit triggers hit \u2014 thesis intact, time remaining, technicals aligned. Hold per plan."
        }
      ],
      "notes": ""
    },
    {
      "id": "GGHRS-M-17C-0821-0702",
      "symbol": "M",
      "strategy": "long_call",
      "strategy_label": "Long Call",
      "group": "GG_High Relative Strength",
      "buy_date": "2026-07-02",
      "expiration": "2026-08-21",
      "dte": 36,
      "contracts": 1,
      "legs": [
        {
          "type": "call",
          "side": "long",
          "strike": 17.0,
          "qty": 1
        }
      ],
      "entry_price": 6.5,
      "mark": 7.65,
      "pl": 115.0,
      "pl_pct": 17.7,
      "technicals": {
        "price": 24.12,
        "rsi": 57.1,
        "sma20": 23.85,
        "sma50": 22.22,
        "macd_hist": -0.132
      },
      "sparkline": [
        6.5,
        6.85,
        6.5,
        5.95,
        5.725,
        5.9,
        6.3,
        6.0,
        6.975,
        7.65
      ],
      "recommendations": [
        {
          "level": "watch",
          "text": "MACD histogram negative \u2014 bullish momentum fading on the daily chart."
        }
      ],
      "notes": ""
    },
    {
      "id": "GGHRS-MCY-90C-0821-0702",
      "symbol": "MCY",
      "strategy": "long_call",
      "strategy_label": "Long Call",
      "group": "GG_High Relative Strength",
      "buy_date": "2026-07-02",
      "expiration": "2026-08-21",
      "dte": 36,
      "contracts": 1,
      "legs": [
        {
          "type": "call",
          "side": "long",
          "strike": 90.0,
          "qty": 1
        }
      ],
      "entry_price": 21.2,
      "mark": 19.15,
      "pl": -205.0,
      "pl_pct": -9.7,
      "technicals": {
        "price": 107.49,
        "rsi": 54.0,
        "sma20": 107.36,
        "sma50": 102.78,
        "macd_hist": -0.505
      },
      "sparkline": [
        21.2,
        22.45,
        22.4,
        21.7,
        21.35,
        20.95,
        21.1,
        19.75,
        17.0,
        19.15
      ],
      "recommendations": [
        {
          "level": "watch",
          "text": "MACD histogram negative \u2014 bullish momentum fading on the daily chart."
        }
      ],
      "notes": ""
    },
    {
      "id": "GGHRS-MET-85C-0821-0702",
      "symbol": "MET",
      "strategy": "long_call",
      "strategy_label": "Long Call",
      "group": "GG_High Relative Strength",
      "buy_date": "2026-07-02",
      "expiration": "2026-08-21",
      "dte": 36,
      "contracts": 1,
      "legs": [
        {
          "type": "call",
          "side": "long",
          "strike": 85.0,
          "qty": 1
        }
      ],
      "entry_price": 6.1,
      "mark": 9.2,
      "pl": 310.0,
      "pl_pct": 50.8,
      "technicals": {
        "price": 93.7,
        "rsi": 68.1,
        "sma20": 88.83,
        "sma50": 85.04,
        "macd_hist": 0.299
      },
      "sparkline": [
        6.1,
        6.9,
        7.85,
        6.55,
        7.5,
        7.85,
        8.85,
        8.55,
        8.35,
        9.2
      ],
      "recommendations": [
        {
          "level": "watch",
          "text": "Up 51% \u2014 profit-target zone. A trailing exit (e.g., give back no more than a third) protects gains."
        }
      ],
      "notes": ""
    },
    {
      "id": "GGHRS-MGM-40C-0821-0702",
      "symbol": "MGM",
      "strategy": "long_call",
      "strategy_label": "Long Call",
      "group": "GG_High Relative Strength",
      "buy_date": "2026-07-02",
      "expiration": "2026-08-21",
      "dte": 36,
      "contracts": 1,
      "legs": [
        {
          "type": "call",
          "side": "long",
          "strike": 40.0,
          "qty": 1
        }
      ],
      "entry_price": 7.7,
      "mark": 7.35,
      "pl": -35.0,
      "pl_pct": -4.5,
      "technicals": {
        "price": 46.9,
        "rsi": 53.4,
        "sma20": 47.2,
        "sma50": 44.24,
        "macd_hist": -0.312
      },
      "sparkline": [
        7.7,
        7.5,
        7.45,
        7.2,
        7.25,
        8.0,
        7.8,
        7.8,
        7.3,
        7.35
      ],
      "recommendations": [
        {
          "level": "warn",
          "text": "Underlying closed below its 20-day SMA \u2014 short-term trend no longer supports the bullish thesis."
        },
        {
          "level": "watch",
          "text": "MACD histogram negative \u2014 bullish momentum fading on the daily chart."
        }
      ],
      "notes": ""
    },
    {
      "id": "GGHRS-MRP-22_5C-0821-0702",
      "symbol": "MRP",
      "strategy": "long_call",
      "strategy_label": "Long Call",
      "group": "GG_High Relative Strength",
      "buy_date": "2026-07-02",
      "expiration": "2026-08-21",
      "dte": 36,
      "contracts": 1,
      "legs": [
        {
          "type": "call",
          "side": "long",
          "strike": 22.5,
          "qty": 1
        }
      ],
      "entry_price": 6.8,
      "mark": 7.2,
      "pl": 40.0,
      "pl_pct": 5.9,
      "technicals": {
        "price": 29.57,
        "rsi": 57.6,
        "sma20": 29.0,
        "sma50": 28.38,
        "macd_hist": -0.034
      },
      "sparkline": [
        6.8,
        6.7,
        6.1,
        6.05,
        6.1,
        6.2,
        6.35,
        5.95,
        6.15,
        7.2
      ],
      "recommendations": [
        {
          "level": "watch",
          "text": "MACD histogram negative \u2014 bullish momentum fading on the daily chart."
        }
      ],
      "notes": ""
    },
    {
      "id": "GGHRS-OII-30C-0821-0702",
      "symbol": "OII",
      "strategy": "long_call",
      "strategy_label": "Long Call",
      "group": "GG_High Relative Strength",
      "buy_date": "2026-07-02",
      "expiration": "2026-08-21",
      "dte": 36,
      "contracts": 1,
      "legs": [
        {
          "type": "call",
          "side": "long",
          "strike": 30.0,
          "qty": 1
        }
      ],
      "entry_price": 8.9,
      "mark": 12.85,
      "pl": 395.0,
      "pl_pct": 44.4,
      "technicals": {
        "price": 42.3,
        "rsi": 61.2,
        "sma20": 39.59,
        "sma50": 38.81,
        "macd_hist": 0.357
      },
      "sparkline": [
        8.9,
        10.0,
        10.2,
        11.4,
        11.45,
        11.95,
        13.6,
        13.5,
        13.3,
        12.85
      ],
      "recommendations": [
        {
          "level": "hold",
          "text": "No exit triggers hit \u2014 thesis intact, time remaining, technicals aligned. Hold per plan."
        }
      ],
      "notes": ""
    },
    {
      "id": "GGHRS-PAAS-35C-0821-0702",
      "symbol": "PAAS",
      "strategy": "long_call",
      "strategy_label": "Long Call",
      "group": "GG_High Relative Strength",
      "buy_date": "2026-07-02",
      "expiration": "2026-08-21",
      "dte": 36,
      "contracts": 1,
      "legs": [
        {
          "type": "call",
          "side": "long",
          "strike": 35.0,
          "qty": 1
        }
      ],
      "entry_price": 11.8,
      "mark": 7.9,
      "pl": -390.0,
      "pl_pct": -33.1,
      "technicals": {
        "price": 41.98,
        "rsi": 36.5,
        "sma20": 45.04,
        "sma50": 50.47,
        "macd_hist": 0.068
      },
      "sparkline": [
        11.8,
        10.6,
        9.7,
        8.4,
        9.65,
        9.4,
        8.45,
        9.3,
        9.0,
        7.9
      ],
      "recommendations": [
        {
          "level": "warn",
          "text": "Underlying closed below its 20-day SMA \u2014 short-term trend no longer supports the bullish thesis."
        },
        {
          "level": "warn",
          "text": "Underlying is below its 50-day SMA \u2014 intermediate trend is down; bullish premium is fighting the tape."
        }
      ],
      "notes": ""
    },
    {
      "id": "SAM1-HPQ-21C-0821-0702",
      "symbol": "HPQ",
      "strategy": "long_call",
      "strategy_label": "Long Call",
      "group": "1 Samurai Scan First",
      "buy_date": "2026-07-02",
      "expiration": "2026-08-21",
      "dte": 36,
      "contracts": 1,
      "legs": [
        {
          "type": "call",
          "side": "long",
          "strike": 21.0,
          "qty": 1
        }
      ],
      "entry_price": 1.94,
      "mark": 3.325,
      "pl": 138.5,
      "pl_pct": 71.4,
      "technicals": {
        "price": 24.14,
        "rsi": 54.1,
        "sma20": 23.32,
        "sma50": 23.57,
        "macd_hist": 0.135
      },
      "sparkline": [
        1.94,
        2.33,
        2.635,
        3.195,
        3.525,
        3.85,
        3.825,
        4.075,
        3.215,
        3.325
      ],
      "recommendations": [
        {
          "level": "watch",
          "text": "Up 71% \u2014 profit-target zone. A trailing exit (e.g., give back no more than a third) protects gains."
        }
      ],
      "notes": ""
    }
  ],
  "closed": [],
  "equity": [
    {
      "date": "2026-07-02",
      "realized": 0,
      "total": -10615.0
    },
    {
      "date": "2026-07-03",
      "realized": 0,
      "total": -12051.5
    },
    {
      "date": "2026-07-06",
      "realized": 0,
      "total": 7582.0
    },
    {
      "date": "2026-07-07",
      "realized": 0,
      "total": -13422.5
    },
    {
      "date": "2026-07-08",
      "realized": 0,
      "total": -7766.5
    },
    {
      "date": "2026-07-09",
      "realized": 0,
      "total": -286.0
    },
    {
      "date": "2026-07-10",
      "realized": 0,
      "total": 4766.5
    },
    {
      "date": "2026-07-13",
      "realized": 0,
      "total": -12639.0
    },
    {
      "date": "2026-07-14",
      "realized": 0,
      "total": -1313.0
    },
    {
      "date": "2026-07-15",
      "realized": 0,
      "total": -10945.5
    },
    {
      "date": "2026-07-16",
      "realized": 0,
      "total": -20925.5
    }
  ]
}